{
    "name": "Aragorn",
    "age": "87",
    "title": "King of Gondor and Arnor",
    "gender": "Male",
    "birthplace": "Rivendell",
    "appearance": "Tall and noble with dark hair and gray eyes",
    "eyecolor": "Gray-blue",
    "haircolor": "Dark brown",
    "height": "6'5\"",
    "species": "Human (Dúnedain)",
    "armor": "Royal armor of Gondor with the white tree emblem",
    "beliefs": "Hope, justice, and the restoration of the kingdoms of Men",
    "powers": "Healing touch, longevity of the Dúnedain, Wisdom",
    "weapons": "Anduril (the Flame of the West), bow and arrows",
    "backstory": "Born in Rivendell as the son of Arathorn, Aragorn was raised by Elrond. A ranger of the North, he traveled the wild lands for many years. He learned of his heritage and destiny, eventually claiming the thrones of both Gondor and Arnor."
}